{
  "id": "strike-ory-provider-secure-js",
  "name": "ory provider secure js",
  "version": "0.1.0",
  "stack": [
    "ory",
    "js"
  ],
  "tags": [
    "provider",
    "secure",
    "generated",
    "strike"
  ],
  "description": "Auto-generated spike for ory provider in js (secure).",
  "params": [
    {
      "name": "app_name",
      "default": "ory-provider-app"
    }
  ],
  "files": [
    {
      "path": "src/ory-provider.js",
      "template": "# Spike: ory provider (js)\n// Auto-generated spike stub for ory (provider)\nmodule.exports = function demo(){\n  console.log('use ory - provider (secure)');\n};\n"
    },
    {
      "path": "spikes/strike-ory-provider-secure-js.js.txt",
      "template": "# Spike: ory provider (js)\n// Auto-generated spike stub for ory (provider)\nmodule.exports = function demo(){\n  console.log('use ory - provider (secure)');\n};\n"
    },
    {
      "path": "spikes/strike-ory-provider-secure-js.md",
      "template": "# ory provider (secure, js)\n\nThis is an auto-generated spike template.\n"
    }
  ],
  "patches": []
}