{
  "id": "strike-nuxt-job-typed-go",
  "name": "nuxt job typed go",
  "version": "0.1.0",
  "stack": [
    "nuxt",
    "go"
  ],
  "tags": [
    "job",
    "typed",
    "generated",
    "strike"
  ],
  "description": "Auto-generated spike for nuxt job in go (typed).",
  "params": [
    {
      "name": "app_name",
      "default": "nuxt-job-app"
    }
  ],
  "files": [
    {
      "path": "spikes/strike-nuxt-job-typed-go.go.txt",
      "template": "# Spike: nuxt job (go)\n// Auto-generated spike stub for nuxt (job)\npackage main\nimport \"fmt\"\nfunc demo(){ fmt.Println(\"use nuxt - job (typed)\") }\n"
    },
    {
      "path": "spikes/strike-nuxt-job-typed-go.md",
      "template": "# nuxt job (typed, go)\n\nThis is an auto-generated spike template.\n"
    }
  ],
  "patches": []
}
