{
  "id": "strike-i18next-init-typed-ts",
  "name": "i18next init typed ts",
  "version": "0.1.0",
  "stack": [
    "i18next",
    "ts"
  ],
  "tags": [
    "init",
    "typed",
    "generated",
    "strike"
  ],
  "description": "Auto-generated spike for i18next init in ts (typed).",
  "params": [
    {
      "name": "app_name",
      "default": "i18next-init-app"
    }
  ],
  "files": [
    {
      "path": "src/i18next-init.ts",
      "template": "# Spike: i18next init (ts)\n// Auto-generated spike stub for i18next (init)\nexport function demo() {\n  console.log('use i18next - init (typed)');\n}\n"
    },
    {
      "path": "src/i18n/i18next.ts",
      "template": "export const i18n = { lng: 'en', resources: { en: { translation: { hello: 'Hello' } } } };\n"
    },
    {
      "path": "spikes/strike-i18next-init-typed-ts.ts.txt",
      "template": "# Spike: i18next init (ts)\n// Auto-generated spike stub for i18next (init)\nexport function demo() {\n  console.log('use i18next - init (typed)');\n}\n"
    },
    {
      "path": "spikes/strike-i18next-init-typed-ts.md",
      "template": "# i18next init (typed, ts)\n\nThis is an auto-generated spike template.\n"
    }
  ],
  "patches": []
}