{
  "id": "strike-react-native-config-typed-js",
  "name": "react-native config typed js",
  "version": "0.1.0",
  "stack": [
    "react-native",
    "js"
  ],
  "tags": [
    "config",
    "typed",
    "generated",
    "strike"
  ],
  "description": "Auto-generated spike for react-native config in js (typed).",
  "params": [
    {
      "name": "app_name",
      "default": "react-native-config-app"
    }
  ],
  "files": [
    {
      "path": "src/react-native-config.js",
      "template": "# Spike: react-native config (js)\n// Auto-generated spike stub for react-native (config)\nmodule.exports = function demo(){\n  console.log('use react-native - config (typed)');\n};\n"
    },
    {
      "path": "spikes/strike-react-native-config-typed-js.js.txt",
      "template": "# Spike: react-native config (js)\n// Auto-generated spike stub for react-native (config)\nmodule.exports = function demo(){\n  console.log('use react-native - config (typed)');\n};\n"
    },
    {
      "path": "spikes/strike-react-native-config-typed-js.md",
      "template": "# react-native config (typed, js)\n\nThis is an auto-generated spike template.\n"
    }
  ],
  "patches": []
}