{
  "id": "strike-tailwindcss-adapter-secure-js",
  "name": "tailwindcss adapter secure js",
  "version": "0.1.0",
  "stack": [
    "tailwindcss",
    "js"
  ],
  "tags": [
    "adapter",
    "secure",
    "generated",
    "strike"
  ],
  "description": "Auto-generated spike for tailwindcss adapter in js (secure).",
  "params": [
    {
      "name": "app_name",
      "default": "tailwindcss-adapter-app"
    }
  ],
  "files": [
    {
      "path": "src/tailwindcss-adapter.js",
      "template": "# Spike: tailwindcss adapter (js)\n// Auto-generated spike stub for tailwindcss (adapter)\nmodule.exports = function demo(){\n  console.log('use tailwindcss - adapter (secure)');\n};\n"
    },
    {
      "path": "spikes/strike-tailwindcss-adapter-secure-js.js.txt",
      "template": "# Spike: tailwindcss adapter (js)\n// Auto-generated spike stub for tailwindcss (adapter)\nmodule.exports = function demo(){\n  console.log('use tailwindcss - adapter (secure)');\n};\n"
    },
    {
      "path": "spikes/strike-tailwindcss-adapter-secure-js.md",
      "template": "# tailwindcss adapter (secure, js)\n\nThis is an auto-generated spike template.\n"
    }
  ],
  "patches": []
}