{
  "id": "strike-nextjs-minimal-basic-ts",
  "name": "nextjs minimal basic ts",
  "version": "0.1.0",
  "stack": [
    "nextjs",
    "ts"
  ],
  "tags": [
    "minimal",
    "basic",
    "generated",
    "strike"
  ],
  "description": "Auto-generated spike for nextjs minimal in ts (basic).",
  "params": [
    {
      "name": "app_name",
      "default": "nextjs-minimal-app"
    }
  ],
  "files": [
    {
      "path": "spikes/strike-nextjs-minimal-basic-ts.ts.txt",
      "template": "# Spike: nextjs minimal (ts)\n// Auto-generated spike stub for nextjs (minimal)\nexport function demo() {\n  console.log('use nextjs - minimal (basic)');\n}\n"
    },
    {
      "path": "spikes/strike-nextjs-minimal-basic-ts.md",
      "template": "# nextjs minimal (basic, ts)\n\nThis is an auto-generated spike template.\n"
    }
  ],
  "patches": []
}
