{
  "id": "strike-angular-hook-basic-rs",
  "name": "angular hook basic rs",
  "version": "0.1.0",
  "stack": [
    "angular",
    "rs"
  ],
  "tags": [
    "hook",
    "basic",
    "generated",
    "strike"
  ],
  "description": "Auto-generated spike for angular hook in rs (basic).",
  "params": [
    {
      "name": "app_name",
      "default": "angular-hook-app"
    }
  ],
  "files": [
    {
      "path": "spikes/strike-angular-hook-basic-rs.rs.txt",
      "template": "# Spike: angular hook (rs)\n// Auto-generated spike stub for angular (hook)\npub fn demo(){ println!(\"use angular - hook (basic)\"); }\n"
    },
    {
      "path": "spikes/strike-angular-hook-basic-rs.md",
      "template": "# angular hook (basic, rs)\n\nThis is an auto-generated spike template.\n"
    }
  ],
  "patches": []
}
