{
  "id": "strike-tailwindcss-component-typed-js",
  "name": "tailwindcss component typed js",
  "version": "0.1.0",
  "stack": [
    "tailwindcss",
    "js"
  ],
  "tags": [
    "component",
    "typed",
    "generated",
    "strike"
  ],
  "description": "Auto-generated spike for tailwindcss component in js (typed).",
  "params": [
    {
      "name": "app_name",
      "default": "tailwindcss-component-app"
    }
  ],
  "files": [
    {
      "path": "src/tailwindcss-component.js",
      "template": "# Spike: tailwindcss component (js)\n// Auto-generated spike stub for tailwindcss (component)\nmodule.exports = function demo(){\n  console.log('use tailwindcss - component (typed)');\n};\n"
    },
    {
      "path": "spikes/strike-tailwindcss-component-typed-js.js.txt",
      "template": "# Spike: tailwindcss component (js)\n// Auto-generated spike stub for tailwindcss (component)\nmodule.exports = function demo(){\n  console.log('use tailwindcss - component (typed)');\n};\n"
    },
    {
      "path": "spikes/strike-tailwindcss-component-typed-js.md",
      "template": "# tailwindcss component (typed, js)\n\nThis is an auto-generated spike template.\n"
    }
  ],
  "patches": []
}