{
  "id": "strike-vue-minimal-advanced-js",
  "name": "vue minimal advanced js",
  "version": "0.1.0",
  "stack": [
    "vue",
    "js"
  ],
  "tags": [
    "minimal",
    "advanced",
    "generated",
    "strike"
  ],
  "description": "Auto-generated spike for vue minimal in js (advanced).",
  "params": [
    {
      "name": "app_name",
      "default": "vue-minimal-app"
    }
  ],
  "files": [
    {
      "path": "spikes/strike-vue-minimal-advanced-js.js.txt",
      "template": "# Spike: vue minimal (js)\n// Auto-generated spike stub for vue (minimal)\nmodule.exports = function demo(){\n  console.log('use vue - minimal (advanced)');\n};\n"
    },
    {
      "path": "spikes/strike-vue-minimal-advanced-js.md",
      "template": "# vue minimal (advanced, js)\n\nThis is an auto-generated spike template.\n"
    }
  ],
  "patches": []
}
