{
  "id": "strike-solid-init-advanced-ts",
  "name": "solid init advanced ts",
  "version": "0.1.0",
  "stack": [
    "solid",
    "ts"
  ],
  "tags": [
    "init",
    "advanced",
    "generated",
    "strike"
  ],
  "description": "Auto-generated spike for solid init in ts (advanced).",
  "params": [
    {
      "name": "app_name",
      "default": "solid-init-app"
    }
  ],
  "files": [
    {
      "path": "spikes/strike-solid-init-advanced-ts.ts.txt",
      "template": "# Spike: solid init (ts)\n// Auto-generated spike stub for solid (init)\nexport function demo() {\n  console.log('use solid - init (advanced)');\n}\n"
    },
    {
      "path": "spikes/strike-solid-init-advanced-ts.md",
      "template": "# solid init (advanced, ts)\n\nThis is an auto-generated spike template.\n"
    }
  ],
  "patches": []
}
