{
  "id": "strike-astro-seed-typed-js",
  "name": "astro seed typed js",
  "version": "0.1.0",
  "stack": [
    "astro",
    "js"
  ],
  "tags": [
    "seed",
    "typed",
    "generated",
    "strike"
  ],
  "description": "Auto-generated spike for astro seed in js (typed).",
  "params": [
    {
      "name": "app_name",
      "default": "astro-seed-app"
    }
  ],
  "files": [
    {
      "path": "spikes/strike-astro-seed-typed-js.js.txt",
      "template": "# Spike: astro seed (js)\n// Auto-generated spike stub for astro (seed)\nmodule.exports = function demo(){\n  console.log('use astro - seed (typed)');\n};\n"
    },
    {
      "path": "spikes/strike-astro-seed-typed-js.md",
      "template": "# astro seed (typed, js)\n\nThis is an auto-generated spike template.\n"
    }
  ],
  "patches": []
}
