{
  "id": "strike-cloudinary-init-typed-ts",
  "name": "cloudinary init typed ts",
  "version": "0.1.0",
  "stack": [
    "cloudinary",
    "ts"
  ],
  "tags": [
    "init",
    "typed",
    "generated",
    "strike"
  ],
  "description": "Auto-generated spike for cloudinary init in ts (typed).",
  "params": [
    {
      "name": "app_name",
      "default": "cloudinary-init-app"
    }
  ],
  "files": [
    {
      "path": "src/cloudinary-init.ts",
      "template": "# Spike: cloudinary init (ts)\n// Auto-generated spike stub for cloudinary (init)\nexport function demo() {\n  console.log('use cloudinary - init (typed)');\n}\n"
    },
    {
      "path": "spikes/strike-cloudinary-init-typed-ts.ts.txt",
      "template": "# Spike: cloudinary init (ts)\n// Auto-generated spike stub for cloudinary (init)\nexport function demo() {\n  console.log('use cloudinary - init (typed)');\n}\n"
    },
    {
      "path": "spikes/strike-cloudinary-init-typed-ts.md",
      "template": "# cloudinary init (typed, ts)\n\nThis is an auto-generated spike template.\n"
    }
  ],
  "patches": []
}