{
  "id": "strike-solid-plugin-basic-kt",
  "name": "solid plugin basic kt",
  "version": "0.1.0",
  "stack": [
    "solid",
    "kt"
  ],
  "tags": [
    "plugin",
    "basic",
    "generated",
    "strike"
  ],
  "description": "Auto-generated spike for solid plugin in kt (basic).",
  "params": [
    {
      "name": "app_name",
      "default": "solid-plugin-app"
    }
  ],
  "files": [
    {
      "path": "spikes/strike-solid-plugin-basic-kt.kt.txt",
      "template": "# Spike: solid plugin (kt)\n// Auto-generated spike stub for solid (plugin)\nfun demo(){ println(\"use solid - plugin (basic)\") }\n"
    },
    {
      "path": "spikes/strike-solid-plugin-basic-kt.md",
      "template": "# solid plugin (basic, kt)\n\nThis is an auto-generated spike template.\n"
    }
  ],
  "patches": []
}
