{
  "id": "strike-react-scheduler-secure-ts",
  "name": "react scheduler secure ts",
  "version": "0.1.0",
  "stack": [
    "react",
    "ts"
  ],
  "tags": [
    "scheduler",
    "secure",
    "generated",
    "strike"
  ],
  "description": "Auto-generated spike for react scheduler in ts (secure).",
  "params": [
    {
      "name": "app_name",
      "default": "react-scheduler-app"
    }
  ],
  "files": [
    {
      "path": "src/react-scheduler.ts",
      "template": "# Spike: react scheduler (ts)\n// Auto-generated spike stub for react (scheduler)\nexport function demo() {\n  console.log('use react - scheduler (secure)');\n}\n"
    },
    {
      "path": "spikes/strike-react-scheduler-secure-ts.ts.txt",
      "template": "# Spike: react scheduler (ts)\n// Auto-generated spike stub for react (scheduler)\nexport function demo() {\n  console.log('use react - scheduler (secure)');\n}\n"
    },
    {
      "path": "spikes/strike-react-scheduler-secure-ts.md",
      "template": "# react scheduler (secure, ts)\n\nThis is an auto-generated spike template.\n"
    }
  ],
  "patches": []
}