{
  "id": "strike-radix-ui-provider-basic-ts",
  "name": "radix-ui provider basic ts",
  "version": "0.1.0",
  "stack": [
    "radix-ui",
    "ts"
  ],
  "tags": [
    "provider",
    "basic",
    "generated",
    "strike"
  ],
  "description": "Auto-generated spike for radix-ui provider in ts (basic).",
  "params": [
    {
      "name": "app_name",
      "default": "radix-ui-provider-app"
    }
  ],
  "files": [
    {
      "path": "src/radix-ui-provider.ts",
      "template": "# Spike: radix-ui provider (ts)\n// Auto-generated spike stub for radix-ui (provider)\nexport function demo() {\n  console.log('use radix-ui - provider (basic)');\n}\n"
    },
    {
      "path": "spikes/strike-radix-ui-provider-basic-ts.ts.txt",
      "template": "# Spike: radix-ui provider (ts)\n// Auto-generated spike stub for radix-ui (provider)\nexport function demo() {\n  console.log('use radix-ui - provider (basic)');\n}\n"
    },
    {
      "path": "spikes/strike-radix-ui-provider-basic-ts.md",
      "template": "# radix-ui provider (basic, ts)\n\nThis is an auto-generated spike template.\n"
    }
  ],
  "patches": []
}