{
  "id": "strike-neo4j-client-basic-ts",
  "name": "neo4j client basic ts",
  "version": "0.1.0",
  "stack": [
    "neo4j",
    "ts"
  ],
  "tags": [
    "client",
    "basic",
    "generated",
    "strike"
  ],
  "description": "Auto-generated spike for neo4j client in ts (basic).",
  "params": [
    {
      "name": "app_name",
      "default": "neo4j-client-app"
    }
  ],
  "files": [
    {
      "path": "src/neo4j-client.ts",
      "template": "# Spike: neo4j client (ts)\n// Auto-generated spike stub for neo4j (client)\nexport function demo() {\n  console.log('use neo4j - client (basic)');\n}\n"
    },
    {
      "path": "spikes/strike-neo4j-client-basic-ts.ts.txt",
      "template": "# Spike: neo4j client (ts)\n// Auto-generated spike stub for neo4j (client)\nexport function demo() {\n  console.log('use neo4j - client (basic)');\n}\n"
    },
    {
      "path": "spikes/strike-neo4j-client-basic-ts.md",
      "template": "# neo4j client (basic, ts)\n\nThis is an auto-generated spike template.\n"
    }
  ],
  "patches": []
}