{
  "id": "strike-pino-middleware-basic-ts",
  "name": "pino middleware basic ts",
  "version": "0.1.0",
  "stack": [
    "pino",
    "ts"
  ],
  "tags": [
    "middleware",
    "basic",
    "generated",
    "strike"
  ],
  "description": "Auto-generated spike for pino middleware in ts (basic).",
  "params": [
    {
      "name": "app_name",
      "default": "pino-middleware-app"
    }
  ],
  "files": [
    {
      "path": "src/pino-middleware.ts",
      "template": "# Spike: pino middleware (ts)\n// Auto-generated spike stub for pino (middleware)\nexport function demo() {\n  console.log('use pino - middleware (basic)');\n}\n"
    },
    {
      "path": "spikes/strike-pino-middleware-basic-ts.ts.txt",
      "template": "# Spike: pino middleware (ts)\n// Auto-generated spike stub for pino (middleware)\nexport function demo() {\n  console.log('use pino - middleware (basic)');\n}\n"
    },
    {
      "path": "spikes/strike-pino-middleware-basic-ts.md",
      "template": "# pino middleware (basic, ts)\n\nThis is an auto-generated spike template.\n"
    }
  ],
  "patches": []
}