{
  "id": "strike-tauri-adapter-secure-ts",
  "name": "tauri adapter secure ts",
  "version": "0.1.0",
  "stack": [
    "tauri",
    "ts"
  ],
  "tags": [
    "adapter",
    "secure",
    "generated",
    "strike"
  ],
  "description": "Auto-generated spike for tauri adapter in ts (secure).",
  "params": [
    {
      "name": "app_name",
      "default": "tauri-adapter-app"
    }
  ],
  "files": [
    {
      "path": "src/tauri-adapter.ts",
      "template": "# Spike: tauri adapter (ts)\n// Auto-generated spike stub for tauri (adapter)\nexport function demo() {\n  console.log('use tauri - adapter (secure)');\n}\n"
    },
    {
      "path": "spikes/strike-tauri-adapter-secure-ts.ts.txt",
      "template": "# Spike: tauri adapter (ts)\n// Auto-generated spike stub for tauri (adapter)\nexport function demo() {\n  console.log('use tauri - adapter (secure)');\n}\n"
    },
    {
      "path": "spikes/strike-tauri-adapter-secure-ts.md",
      "template": "# tauri adapter (secure, ts)\n\nThis is an auto-generated spike template.\n"
    }
  ],
  "patches": []
}