{
  "id": "strike-nextjs-init-secure-go",
  "name": "nextjs init secure go",
  "version": "0.1.0",
  "stack": [
    "nextjs",
    "go"
  ],
  "tags": [
    "init",
    "secure",
    "generated",
    "strike"
  ],
  "description": "Auto-generated spike for nextjs init in go (secure).",
  "params": [
    {
      "name": "app_name",
      "default": "nextjs-init-app"
    }
  ],
  "files": [
    {
      "path": "middleware.ts",
      "template": "import { NextResponse } from 'next/server';\nexport function middleware(){ return NextResponse.next(); }\n"
    },
    {
      "path": "spikes/strike-nextjs-init-secure-go.go.txt",
      "template": "# Spike: nextjs init (go)\n// Auto-generated spike stub for nextjs (init)\npackage main\nimport \"fmt\"\nfunc demo(){ fmt.Println(\"use nextjs - init (secure)\") }\n"
    },
    {
      "path": "spikes/strike-nextjs-init-secure-go.md",
      "template": "# nextjs init (secure, go)\n\nThis is an auto-generated spike template.\n"
    }
  ],
  "patches": []
}
