{
  "id": "strike-expo-command-secure-js",
  "name": "expo command secure js",
  "version": "0.1.0",
  "stack": [
    "expo",
    "js"
  ],
  "tags": [
    "command",
    "secure",
    "generated",
    "strike"
  ],
  "description": "Auto-generated spike for expo command in js (secure).",
  "params": [
    {
      "name": "app_name",
      "default": "expo-command-app"
    }
  ],
  "files": [
    {
      "path": "src/expo-command.js",
      "template": "# Spike: expo command (js)\n// Auto-generated spike stub for expo (command)\nmodule.exports = function demo(){\n  console.log('use expo - command (secure)');\n};\n"
    },
    {
      "path": "spikes/strike-expo-command-secure-js.js.txt",
      "template": "# Spike: expo command (js)\n// Auto-generated spike stub for expo (command)\nmodule.exports = function demo(){\n  console.log('use expo - command (secure)');\n};\n"
    },
    {
      "path": "spikes/strike-expo-command-secure-js.md",
      "template": "# expo command (secure, js)\n\nThis is an auto-generated spike template.\n"
    }
  ],
  "patches": []
}