{
  "id": "strike-terraform-worker-typed-ts",
  "name": "terraform worker typed ts",
  "version": "0.1.0",
  "stack": [
    "terraform",
    "ts"
  ],
  "tags": [
    "worker",
    "typed",
    "generated",
    "strike"
  ],
  "description": "Auto-generated spike for terraform worker in ts (typed).",
  "params": [
    {
      "name": "app_name",
      "default": "terraform-worker-app"
    }
  ],
  "files": [
    {
      "path": "src/terraform-worker.ts",
      "template": "# Spike: terraform worker (ts)\n// Auto-generated spike stub for terraform (worker)\nexport function demo() {\n  console.log('use terraform - worker (typed)');\n}\n"
    },
    {
      "path": "spikes/strike-terraform-worker-typed-ts.ts.txt",
      "template": "# Spike: terraform worker (ts)\n// Auto-generated spike stub for terraform (worker)\nexport function demo() {\n  console.log('use terraform - worker (typed)');\n}\n"
    },
    {
      "path": "spikes/strike-terraform-worker-typed-ts.md",
      "template": "# terraform worker (typed, ts)\n\nThis is an auto-generated spike template.\n"
    }
  ],
  "patches": []
}