{
  "id": "strike-fastify-adapter-typed-kt",
  "name": "fastify adapter typed kt",
  "version": "0.1.0",
  "stack": [
    "fastify",
    "kt"
  ],
  "tags": [
    "adapter",
    "typed",
    "generated",
    "strike"
  ],
  "description": "Auto-generated spike for fastify adapter in kt (typed).",
  "params": [
    {
      "name": "app_name",
      "default": "fastify-adapter-app"
    }
  ],
  "files": [
    {
      "path": "spikes/strike-fastify-adapter-typed-kt.kt.txt",
      "template": "# Spike: fastify adapter (kt)\n// Auto-generated spike stub for fastify (adapter)\nfun demo(){ println(\"use fastify - adapter (typed)\") }\n"
    },
    {
      "path": "spikes/strike-fastify-adapter-typed-kt.md",
      "template": "# fastify adapter (typed, kt)\n\nThis is an auto-generated spike template.\n"
    }
  ],
  "patches": []
}
