{
  "id": "strike-remix-hook-secure-js",
  "name": "remix hook secure js",
  "version": "0.1.0",
  "stack": [
    "remix",
    "js"
  ],
  "tags": [
    "hook",
    "secure",
    "generated",
    "strike"
  ],
  "description": "Auto-generated spike for remix hook in js (secure).",
  "params": [
    {
      "name": "app_name",
      "default": "remix-hook-app"
    }
  ],
  "files": [
    {
      "path": "spikes/strike-remix-hook-secure-js.js.txt",
      "template": "# Spike: remix hook (js)\n// Auto-generated spike stub for remix (hook)\nmodule.exports = function demo(){\n  console.log('use remix - hook (secure)');\n};\n"
    },
    {
      "path": "spikes/strike-remix-hook-secure-js.md",
      "template": "# remix hook (secure, js)\n\nThis is an auto-generated spike template.\n"
    }
  ],
  "patches": []
}
