{
  "id": "strike-koa-init-basic-kt",
  "name": "koa init basic kt",
  "version": "0.1.0",
  "stack": [
    "koa",
    "kt"
  ],
  "tags": [
    "init",
    "basic",
    "generated",
    "strike"
  ],
  "description": "Auto-generated spike for koa init in kt (basic).",
  "params": [
    {
      "name": "app_name",
      "default": "koa-init-app"
    }
  ],
  "files": [
    {
      "path": "spikes/strike-koa-init-basic-kt.kt.txt",
      "template": "# Spike: koa init (kt)\n// Auto-generated spike stub for koa (init)\nfun demo(){ println(\"use koa - init (basic)\") }\n"
    },
    {
      "path": "spikes/strike-koa-init-basic-kt.md",
      "template": "# koa init (basic, kt)\n\nThis is an auto-generated spike template.\n"
    }
  ],
  "patches": []
}
