{
  "id": "strike-react-provider-typed-ts",
  "name": "react provider typed ts",
  "version": "0.1.0",
  "stack": [
    "react",
    "ts"
  ],
  "tags": [
    "provider",
    "typed",
    "generated",
    "strike"
  ],
  "description": "Auto-generated spike for react provider in ts (typed).",
  "params": [
    {
      "name": "app_name",
      "default": "react-provider-app"
    }
  ],
  "files": [
    {
      "path": "spikes/strike-react-provider-typed-ts.ts.txt",
      "template": "# Spike: react provider (ts)\n// Auto-generated spike stub for react (provider)\nexport function demo() {\n  console.log('use react - provider (typed)');\n}\n"
    },
    {
      "path": "spikes/strike-react-provider-typed-ts.md",
      "template": "# react provider (typed, ts)\n\nThis is an auto-generated spike template.\n"
    }
  ],
  "patches": []
}
