{
  "id": "strike-gcp-cloud-functions-command-secure-ts",
  "name": "gcp-cloud-functions command secure ts",
  "version": "0.1.0",
  "stack": [
    "gcp-cloud-functions",
    "ts"
  ],
  "tags": [
    "command",
    "secure",
    "generated",
    "strike"
  ],
  "description": "Auto-generated spike for gcp-cloud-functions command in ts (secure).",
  "params": [
    {
      "name": "app_name",
      "default": "gcp-cloud-functions-command-app"
    }
  ],
  "files": [
    {
      "path": "src/gcp-cloud-functions-command.ts",
      "template": "# Spike: gcp-cloud-functions command (ts)\n// Auto-generated spike stub for gcp-cloud-functions (command)\nexport function demo() {\n  console.log('use gcp-cloud-functions - command (secure)');\n}\n"
    },
    {
      "path": "spikes/strike-gcp-cloud-functions-command-secure-ts.ts.txt",
      "template": "# Spike: gcp-cloud-functions command (ts)\n// Auto-generated spike stub for gcp-cloud-functions (command)\nexport function demo() {\n  console.log('use gcp-cloud-functions - command (secure)');\n}\n"
    },
    {
      "path": "spikes/strike-gcp-cloud-functions-command-secure-ts.md",
      "template": "# gcp-cloud-functions command (secure, ts)\n\nThis is an auto-generated spike template.\n"
    }
  ],
  "patches": []
}