{
  "id": "strike-k6-client-advanced-ts",
  "name": "k6 client advanced ts",
  "version": "0.1.0",
  "stack": [
    "k6",
    "ts"
  ],
  "tags": [
    "client",
    "advanced",
    "generated",
    "strike"
  ],
  "description": "Auto-generated spike for k6 client in ts (advanced).",
  "params": [
    {
      "name": "app_name",
      "default": "k6-client-app"
    }
  ],
  "files": [
    {
      "path": "src/k6-client.ts",
      "template": "# Spike: k6 client (ts)\n// Auto-generated spike stub for k6 (client)\nexport function demo() {\n  console.log('use k6 - client (advanced)');\n}\n"
    },
    {
      "path": "spikes/strike-k6-client-advanced-ts.ts.txt",
      "template": "# Spike: k6 client (ts)\n// Auto-generated spike stub for k6 (client)\nexport function demo() {\n  console.log('use k6 - client (advanced)');\n}\n"
    },
    {
      "path": "spikes/strike-k6-client-advanced-ts.md",
      "template": "# k6 client (advanced, ts)\n\nThis is an auto-generated spike template.\n"
    }
  ],
  "patches": []
}