{
  "id": "strike-ghost-provider-secure-ts",
  "name": "ghost provider secure ts",
  "version": "0.1.0",
  "stack": [
    "ghost",
    "ts"
  ],
  "tags": [
    "provider",
    "secure",
    "generated",
    "strike"
  ],
  "description": "Auto-generated spike for ghost provider in ts (secure).",
  "params": [
    {
      "name": "app_name",
      "default": "ghost-provider-app"
    }
  ],
  "files": [
    {
      "path": "src/ghost-provider.ts",
      "template": "# Spike: ghost provider (ts)\n// Auto-generated spike stub for ghost (provider)\nexport function demo() {\n  console.log('use ghost - provider (secure)');\n}\n"
    },
    {
      "path": "spikes/strike-ghost-provider-secure-ts.ts.txt",
      "template": "# Spike: ghost provider (ts)\n// Auto-generated spike stub for ghost (provider)\nexport function demo() {\n  console.log('use ghost - provider (secure)');\n}\n"
    },
    {
      "path": "spikes/strike-ghost-provider-secure-ts.md",
      "template": "# ghost provider (secure, ts)\n\nThis is an auto-generated spike template.\n"
    }
  ],
  "patches": []
}